{"type":"FeatureCollection","crs":{"type":"name","properties":{"name":"EPSG:4326"}},"features":[{"properties":{"OBJECTID":11518,"eigenaar":"Westtoer","mobility":"Fiets","pid":"1006262-1006313","begin_geoid":"1006262","end_geoid":"1006313","begin_partnerid":"1006262","end_partnerid":"1006313","routetype":"route","direction":"","meldpunt":"http://www.westtoer.be/nl/routechirurg","naam":"West-Vlaanderen","regioURL":"http://www.westtoer.be","shopURL":"https://shop.westtoer.be/nl","updatedate":"2020-04-30","Shape_Length":161.0184647548013},"geometry":{"type":"LineString","coordinates":[[2.8542742903807587,51.03035993210461],[2.854254390209522,51.03023983139051],[2.8541113905872173,51.02937633163118],[2.8540961904375557,51.02928423135088],[2.8540445911781225,51.02891983166928]]}}]}