{"type":"FeatureCollection","crs":{"type":"name","properties":{"name":"EPSG:4326"}},"features":[{"properties":{"OBJECTID":10971,"eigenaar":"Westtoer","mobility":"Fiets","pid":"1006063-1006096","begin_geoid":"1006063","end_geoid":"1006096","begin_partnerid":"1006063","end_partnerid":"1006096","routetype":"route","direction":"","meldpunt":"http://www.westtoer.be/nl/routechirurg","naam":"West-Vlaanderen","regioURL":"http://www.westtoer.be","shopURL":"https://shop.westtoer.be/nl","updatedate":"2020-04-30","Shape_Length":347.45210137518393},"geometry":{"type":"LineString","coordinates":[[3.339583495832794,51.25051297429525],[3.3395835005617176,51.25051288983838],[3.339665200959615,51.25049969025642],[3.3397182004683934,51.250487090621355],[3.343968903019559,51.249059391112255],[3.3439750977559433,51.24905157474121]]}}]}