{"type":"FeatureCollection","crs":{"type":"name","properties":{"name":"EPSG:4326"}},"features":[{"properties":{"OBJECTID":17687,"eigenaar":"Toerisme Provincie Antwerpen","mobility":"Fiets","pid":"1230286-1230312","begin_geoid":"1230286","end_geoid":"1230312","begin_partnerid":"3074335","end_partnerid":"3074373","routetype":"route","direction":null,"meldpunt":"http://www.routedokter.be/","naam":"Fietsnetwerk","regioURL":"http://www.provincieantwerpen.be","shopURL":"","updatedate":"2020-04-30","Shape_Length":2122.383569933927},"geometry":{"type":"LineString","coordinates":[[4.606596985905996,51.159981976785375],[4.601812378084364,51.15761370566204],[4.584388744764398,51.1515034503857],[4.582266026682375,51.150519209040304],[4.58154557780159,51.14997408288718],[4.581835013969457,51.149693009339174]]}}]}