{"type":"FeatureCollection","crs":{"type":"name","properties":{"name":"EPSG:4326"}},"features":[{"properties":{"OBJECTID":18173,"eigenaar":"Toerisme Provincie Antwerpen","mobility":"Fiets","pid":"3408011-3408012","begin_geoid":"3408011","end_geoid":"3408012","begin_partnerid":"3109432","end_partnerid":"3109433","routetype":"route","direction":null,"meldpunt":"http://www.routedokter.be/","naam":"Fietsnetwerk","regioURL":"http://www.provincieantwerpen.be","shopURL":"","updatedate":"2020-04-30","Shape_Length":50.03849805825495},"geometry":{"type":"LineString","coordinates":[[4.8257276143242365,51.35784607966075],[4.825859038201583,51.35740393102631]]}}]}