{"type":"FeatureCollection","crs":{"type":"name","properties":{"name":"EPSG:4326"}},"features":[{"properties":{"OBJECTID":1295,"eigenaar":"Toerisme Provincie Antwerpen","mobility":"Fiets","pid":"4058-3408058","begin_geoid":"4058","end_geoid":"3408058","begin_partnerid":"3054910","end_partnerid":"3113480","routetype":"route","direction":null,"meldpunt":"http://www.routedokter.be/","naam":"Fietsnetwerk","regioURL":"http://www.provincieantwerpen.be","shopURL":"","updatedate":"2020-04-30","Shape_Length":27.504706936155866},"geometry":{"type":"LineString","coordinates":[[4.611216930738058,51.231160500074246],[4.611280172042325,51.231181819063785],[4.611485347460734,51.23120780668772],[4.6115979971089365,51.23120617529558]]}}]}