{"type":"FeatureCollection","crs":{"type":"name","properties":{"name":"EPSG:4326"}},"features":[{"properties":{"OBJECTID":12737,"eigenaar":"Toerisme Provincie Antwerpen","mobility":"Fiets","pid":"5622-1230353","begin_geoid":"1230353","end_geoid":"5622","begin_partnerid":"3054688","end_partnerid":"3054682","routetype":"route","direction":null,"meldpunt":"http://www.routedokter.be/","naam":"Fietsnetwerk","regioURL":"http://www.provincieantwerpen.be","shopURL":"","updatedate":"2020-04-30","Shape_Length":250.8975655213528},"geometry":{"type":"LineString","coordinates":[[5.114030047254733,51.125131019755216],[5.115630035549133,51.1231130154569]]}}]}