{"type":"FeatureCollection","crs":{"type":"name","properties":{"name":"EPSG:4326"}},"features":[{"properties":{"OBJECTID":9747,"eigenaar":"Toerisme Provincie Antwerpen","mobility":"Fiets","pid":"6464-1230342","begin_geoid":"1230342","end_geoid":"6464","begin_partnerid":"3054510","end_partnerid":"3054509","routetype":"route","direction":null,"meldpunt":"http://www.routedokter.be/","naam":"Fietsnetwerk","regioURL":"http://www.provincieantwerpen.be","shopURL":"","updatedate":"2020-04-30","Shape_Length":49.44247131331343},"geometry":{"type":"LineString","coordinates":[[4.4448159727263485,51.03968497801508],[4.444275006894038,51.03940001337217]]}}]}