{"type":"FeatureCollection","crs":{"type":"name","properties":{"name":"EPSG:4326"}},"features":[{"properties":{"OBJECTID":16316,"eigenaar":"Toerisme Oost-Vlaanderen","mobility":"Fiets","pid":"8433-10832","begin_geoid":"10832","end_geoid":"8433","begin_partnerid":"2141030","end_partnerid":"2140987","routetype":"route","direction":"","meldpunt":"http://www.tov.be/nl/routedokter","naam":"Vlaamse Ardennen","regioURL":"http://www.toerismevlaamseardennen.be","shopURL":"http://www.tov.be/nl/webshop","updatedate":"2020-04-30","Shape_Length":583.0953666037481},"geometry":{"type":"LineString","coordinates":[[3.5528997295064695,50.74127133104372],[3.556207950416638,50.741191136295356],[3.560032572333546,50.74102842047117],[3.5611483935757966,50.74099351029436]]}}]}