{"type":"FeatureCollection","crs":{"type":"name","properties":{"name":"EPSG:4326"}},"features":[{"properties":{"OBJECTID":13778,"eigenaar":"Toerisme Oost-Vlaanderen","mobility":"Fiets","pid":"9904-3628241","begin_geoid":"3628241","end_geoid":"9904","begin_partnerid":"2141137","end_partnerid":"2140807","routetype":"route","direction":"","meldpunt":"http://www.tov.be/nl/routedokter","naam":"Waasland","regioURL":"http://www.toerismewaasland.be","shopURL":"http://www.tov.be/nl/webshop","updatedate":"2020-04-30","Shape_Length":1506.5173985723168},"geometry":{"type":"LineString","coordinates":[[3.892689025998123,51.17574153324609],[3.9142266225482305,51.17602793543353]]}}]}